{
    "core": {
        "serial_num": "20683699424D",
        "widget": "False"
    },
    "user": {
        "KU01": {
            "name": "ПК1",
            "state": 1,
            "tooltip": "<html><head/><body><p>Задействовать 1й полукоиплект</p></body></html>"
        },
        "KU02": {
            "name": "Откл",
            "state": 1,
            "tooltip": "<html><head/><body><p>Отключить БЭ</p></body></html>"
        },
        "KU03": {
            "name": "ПК2",
            "state": 1,
            "tooltip": "<html><head/><body><p>Задействовать 2й полукоиплект</p></body></html>"
        },
        "KU04": {
            "name": "",
            "state": 0,
            "tooltip": ""
        },
        "KU05": {
            "name": "К1",
            "state": 1,
            "tooltip": "<html><head/><body><p> </p></body></html>"
        },
        "KU06": {
            "name": "",
            "state": 0,
            "tooltip": ""
        },
        "KU07": {
            "name": "К2",
            "state": 1,
            "tooltip": "<html><head/><body><p> </p></body></html>"
        },
        "KU08": {
            "name": "",
            "state": 0,
            "tooltip": ""
        },
        "KU09": {
            "name": "",
            "state": 0,
            "tooltip": ""
        },
        "KU10": {
            "name": "",
            "state": 0,
            "tooltip": ""
        },
        "KU11": {
            "name": "",
            "state": 0,
            "tooltip": ""
        },
        "KU12": {
            "name": "",
            "state": 0,
            "tooltip": ""
        },
        "KU13": {
            "name": "",
            "state": 0,
            "tooltip": ""
        },
        "KU14": {
            "name": "",
            "state": 0,
            "tooltip": ""
        },
        "KU15": {
            "name": "",
            "state": 0,
            "tooltip": ""
        },
        "KU16": {
            "name": "",
            "state": 0,
            "tooltip": ""
        },
        "T": 100
    }
}